[
  {
    "color": "darkorange",
    "value": -0.17724762628783441
  },
  {
    "color": "steelblue",
    "value": 0.6405760232247877
  },
  {
    "color": "steelblue",
    "value": 0.9677432422067576
  },
  {
    "color": "darkorange",
    "value": -0.4971569937700866
  },
  {
    "color": "darkorange",
    "value": -0.320648360821169
  },
  {
    "color": "darkorange",
    "value": -0.6389430706969228
  },
  {
    "color": "steelblue",
    "value": 0.6033715742417596
  },
  {
    "color": "darkorange",
    "value": -0.1256778062281907
  },
  {
    "color": "steelblue",
    "value": 0.22145102539271466
  },
  {
    "color": "steelblue",
    "value": 0.8449767828190256
  }
]
